pauli_prop-0.1.0.dist-info/METADATA
pauli_prop-0.1.0.dist-info/WHEEL
pauli_prop-0.1.0.dist-info/licenses/LICENSE.txt
pauli_prop/__init__.py
pauli_prop/_accelerate.pyd
pauli_prop/propagation.py
pauli_prop-0.1.0.dist-info/RECORD
