Metadata-Version: 2.4
Name: pauli-prop
Version: 0.1.0
Classifier: Intended Audience :: Developers
Classifier: Intended Audience :: Science/Research
Classifier: License :: OSI Approved :: Apache Software License
Classifier: Natural Language :: English
Classifier: Operating System :: POSIX :: Linux
Classifier: Programming Language :: Python :: 3.10
Classifier: Programming Language :: Python :: 3.11
Classifier: Programming Language :: Python :: 3.12
Classifier: Topic :: Scientific/Engineering :: Physics
Requires-Dist: qiskit>=2.1.2,<3
Requires-Dist: numpy>=1.26
Requires-Dist: qiskit-aer>=0.17.1
Requires-Dist: pauli-prop[test,nbtest,lint,docs] ; extra == 'dev'
Requires-Dist: tox>=4.4.3 ; extra == 'dev'
Requires-Dist: pytest>=8.0 ; extra == 'basetest'
Requires-Dist: pytest-cov>=5.0 ; extra == 'basetest'
Requires-Dist: pauli-prop[basetest] ; extra == 'test'
Requires-Dist: pauli-prop[basetest] ; extra == 'nbtest'
Requires-Dist: nbmake>=1.5.0 ; extra == 'nbtest'
Requires-Dist: ruff==0.14.3 ; extra == 'style'
Requires-Dist: nbqa>=1.8.5 ; extra == 'style'
Requires-Dist: pauli-prop[style] ; extra == 'lint'
Requires-Dist: mypy==1.18.2 ; extra == 'lint'
Requires-Dist: pylint==4.0.2 ; extra == 'lint'
Requires-Dist: reno>=4.1 ; extra == 'lint'
Requires-Dist: toml>=0.9.6 ; extra == 'lint'
Requires-Dist: pauli-prop ; extra == 'notebook-dependencies'
Requires-Dist: matplotlib ; extra == 'notebook-dependencies'
Requires-Dist: qiskit-ibm-runtime ; extra == 'notebook-dependencies'
Requires-Dist: rustworkx ; extra == 'notebook-dependencies'
Requires-Dist: ipywidgets ; extra == 'notebook-dependencies'
Requires-Dist: pylatexenc ; extra == 'notebook-dependencies'
Requires-Dist: pauli-prop[test,notebook-dependencies] ; extra == 'docs'
Requires-Dist: qiskit-sphinx-theme~=2.0.0 ; extra == 'docs'
Requires-Dist: matplotlib ; extra == 'docs'
Requires-Dist: jupyter-sphinx ; extra == 'docs'
Requires-Dist: sphinx-design ; extra == 'docs'
Requires-Dist: sphinx-autodoc-typehints ; extra == 'docs'
Requires-Dist: sphinx-copybutton ; extra == 'docs'
Requires-Dist: sphinx-reredirects ; extra == 'docs'
Requires-Dist: nbsphinx>=0.9.4 ; extra == 'docs'
Requires-Dist: reno>=4.1 ; extra == 'docs'
Provides-Extra: dev
Provides-Extra: basetest
Provides-Extra: test
Provides-Extra: nbtest
Provides-Extra: style
Provides-Extra: lint
Provides-Extra: notebook-dependencies
Provides-Extra: docs
License-File: LICENSE.txt
Summary: Library for performing Pauli propagation.
Requires-Python: >=3.10
